README.md
setup.py
TransportationProblem.egg-info/PKG-INFO
TransportationProblem.egg-info/SOURCES.txt
TransportationProblem.egg-info/dependency_links.txt
TransportationProblem.egg-info/requires.txt
TransportationProblem.egg-info/top_level.txt
transportation_problem/__init__.py
transportation_problem/checker.py
transportation_problem/closed_loop_method.py
transportation_problem/initer.py
transportation_problem/optimizer.py
transportation_problem/problem.py