Metadata-Version: 2.1
Name: TransportationProblem
Version: 0.0.2
Summary: 求解产销平衡的运输问题。
Home-page: https://github.com/cdfmlr/TransportationProblem/
Author: CDFMLR
Author-email: cdfmlr@163.com
License: MIT
Platform: UNKNOWN
